example_pkg/__init__.py
WHPython-0.0.1.dist-info/LICENSE
WHPython-0.0.1.dist-info/METADATA
WHPython-0.0.1.dist-info/WHEEL
WHPython-0.0.1.dist-info/top_level.txt
WHPython-0.0.1.dist-info/RECORD
