Metadata-Version: 2.1
Name: WHPython
Version: 0.0.1
Summary: 文华数据接口
Home-page: https://github.com/pypa/sampleproject
Author: sunsc
Author-email: sunshaoc@wenhua.com.cn
License: UNKNOWN
Platform: UNKNOWN
Classifier: Programming Language :: Python :: 3
Classifier: License :: OSI Approved :: MIT License
Classifier: Operating System :: OS Independent
License-File: LICENSE
